.gitignore
CHANGES.rst
MANIFEST.in
README.rst
README.txt
TODO.txt
bootstrap.py
buildout.cfg
setup.py
collective/__init__.py
collective.setdefaulteditor.egg-info/PKG-INFO
collective.setdefaulteditor.egg-info/SOURCES.txt
collective.setdefaulteditor.egg-info/dependency_links.txt
collective.setdefaulteditor.egg-info/entry_points.txt
collective.setdefaulteditor.egg-info/namespace_packages.txt
collective.setdefaulteditor.egg-info/not-zip-safe
collective.setdefaulteditor.egg-info/requires.txt
collective.setdefaulteditor.egg-info/top_level.txt
collective/setdefaulteditor/__init__.py
collective/setdefaulteditor/browser.py
collective/setdefaulteditor/configure.zcml
collective/setdefaulteditor/form.pt
collective/setdefaulteditor/utils.py
docs/HISTORY.txt
docs/INSTALL.txt
docs/LICENSE.GPL
docs/LICENSE.txt