Metadata-Version: 1.1
Name: collective.setdefaulteditor
Version: 1.5
Summary: Set the default editor in Plone for all existing members.
Home-page: https://github.com/zestsoftware/collective.setdefaulteditor
Author: Maurits van Rees
Author-email: m.van.rees@zestsoftware.nl
License: GPL
Platform: UNKNOWN
Classifier: Framework :: Plone
Classifier: Framework :: Plone :: 3.3
Classifier: Framework :: Plone :: 4.0
Classifier: Framework :: Plone :: 4.1
Classifier: Framework :: Plone :: 4.2
Classifier: Framework :: Plone :: 4.3
Classifier: Programming Language :: Python
